{"text": ["Des", "SLN", "ont", "été", "identifiés", "chez", "662", "patients", "sur", "697", "(95%),", "et", "des", "SLN", "positifs", "ont", "été", "trouvés", "chez", "189", "patients", "sur", "662", "(28,5%)."], "label": ["O", "O", "O", "O", "O", "O", "O", "O", "O", "O", "O", "O", "O", "O", "O", "O", "O", "O", "O", "O", "O", "O", "O", "O"]}
{"text": ["L'", "analyse", "était", "par", "intention", "de", "traiter."], "label": ["O", "O", "O", "O", "O", "O", "O"]}
{"text": ["Les", "taux", "d'", "utilisation", "des", "ressources", "étaient", "statistiquement", "plus", "élevés", "pour", "le", "pemetrexed", "que", "pour", "le", "placebo:", "admissions", "à", "l'", "hôpital", "pour", "des", "effets", "indésirables", "liés", "au", "médicament", "(19", "[", "4", "%", "]", "contre", "aucun", "\";", "\"", "p=0·001", "),", "transfusions", "(42", "[", "10", "%", "]", "contre", "sept", "[", "3", "%", "]", "\";", "\"", "p=0·003", "),", "et", "agents", "stimulant", "l'", "érythropoïèse", "(26", "[", "6", "%", "]", "contre", "quatre", "[", "2", "%", "]", "\";", "\"", "p=0·017", ")."], "label": ["B-Premise", "I-Premise", "I-Premise", "I-Premise", "I-Premise", "I-Premise", "I-Premise", "I-Premise", "I-Premise", "I-Premise", "I-Premise", "I-Premise", "I-Premise", "I-Premise", "I-Premise", "I-Premise", "I-Premise", "I-Premise", "I-Premise", "I-Premise", "I-Premise", "I-Premise", "I-Premise", "I-Premise", "I-Premise", "I-Premise", "I-Premise", "I-Premise", "I-Premise", "I-Premise", "I-Premise", "I-Premise", "I-Premise", "I-Premise", "I-Premise", "I-Premise", "I-Premise", "I-Premise", "I-Premise", "I-Premise", "I-Premise", "I-Premise", "I-Premise", "I-Premise", "I-Premise", "I-Premise", "I-Premise", "I-Premise", "I-Premise", "I-Premise", "I-Premise", "I-Premise", "I-Premise", "I-Premise", "I-Premise", "I-Premise", "I-Premise", "I-Premise", "I-Premise", "I-Premise", "I-Premise", "I-Premise", "I-Premise", "I-Premise", "I-Premise", "I-Premise", "I-Premise", "I-Premise", "I-Premise", "I-Premise", "I-Premise", "I-Premise", "I-Premise", "I-Premise", "I-Premise"]}
{"text": ["Après", "la", "documentation", "de", "la", "maladie", "N2", "par", "médiastinoscopie", "ou", "médiastinotomie", "antérieure,", "les", "patients", "ont", "reçu", "une", "chimiothérapie", "d'", "induction", "avec", "du", "cisplatine,", "de", "la", "vinblastine", "et", "de", "la", "mitomycine-C.", "La", "mitomycine-C", "a", "ensuite", "été", "retirée", "du", "schéma", "d'", "induction."], "label": ["O", "O", "O", "O", "O", "O", "O", "O", "O", "O", "O", "O", "O", "O", "O", "O", "O", "O", "O", "O", "O", "O", "O", "O", "O", "O", "O", "O", "O", "O", "O", "O", "O", "O", "O", "O", "O", "O", "O", "O"]}
{"text": ["L'", "objectif", "était", "d'", "exclure", "une", "diminution", "de", "5%", "du", "taux", "de", "survie", "sans", "progression", "à", "2", "ans", "(SPF)."], "label": ["O", "O", "O", "O", "O", "O", "O", "O", "O", "O", "O", "O", "O", "O", "O", "O", "O", "O", "O"]}
{"text": ["L'", "erlotinib", "était", "supérieur", "au", "placebo", "pour", "la", "survie,", "la", "survie", "sans", "progression", "et", "le", "taux", "de", "réponse", "tumorale."], "label": ["B-Claim", "I-Claim", "I-Claim", "I-Claim", "I-Claim", "I-Claim", "I-Claim", "I-Claim", "I-Claim", "I-Claim", "I-Claim", "I-Claim", "I-Claim", "I-Claim", "I-Claim", "I-Claim", "I-Claim", "I-Claim", "I-Claim"]}
{"text": ["Leur", "âge", "médian", "était", "de", "65", "ans,", "30%", "avaient", "une", "PS2", "et", "76%", "une", "maladie", "au", "stade", "IV."], "label": ["O", "O", "O", "O", "O", "O", "O", "O", "O", "O", "O", "O", "O", "O", "O", "O", "O", "O"]}
{"text": ["En", "conclusion,", "le", "traitement", "par", "le", "carboplatine", "et", "l'", "etoposide", "peut", "améliorer", "la", "qualité", "de", "vie", "et", "la", "survie", "des", "patients", "atteints", "d'", "un", "NSCLC", "avancé."], "label": ["B-Claim", "I-Claim", "I-Claim", "I-Claim", "I-Claim", "I-Claim", "I-Claim", "I-Claim", "I-Claim", "I-Claim", "I-Claim", "I-Claim", "I-Claim", "I-Claim", "I-Claim", "I-Claim", "I-Claim", "I-Claim", "I-Claim", "I-Claim", "I-Claim", "I-Claim", "I-Claim", "I-Claim", "I-Claim", "I-Claim"]}
{"text": ["La", "combinaison", "de", "mouvement", "auto-dirigé", "et", "de", "pleine", "conscience,", "comme", "testé", "ici,", "peut", "être", "un", "outil", "précieux", "pour", "promouvoir", "la", "santé", "et", "le", "bien-être", "chez", "les", "personnes", "âgées", "ayant", "survécu", "à", "long", "terme", "à", "un", "cancer", "du", "sein."], "label": ["B-Claim", "I-Claim", "I-Claim", "I-Claim", "I-Claim", "I-Claim", "I-Claim", "I-Claim", "I-Claim", "I-Claim", "I-Claim", "I-Claim", "I-Claim", "I-Claim", "I-Claim", "I-Claim", "I-Claim", "I-Claim", "I-Claim", "I-Claim", "I-Claim", "I-Claim", "I-Claim", "I-Claim", "I-Claim", "I-Claim", "I-Claim", "I-Claim", "I-Claim", "I-Claim", "I-Claim", "I-Claim", "I-Claim", "I-Claim", "I-Claim", "I-Claim", "I-Claim", "I-Claim"]}
{"text": ["Cependant,", "les", "auto-évaluations", "des", "patients", "ont", "suggéré", "un", "avantage", "possible", "pour", "l'", "AM", "qui", "est", "en", "cours", "d'", "exploration", "avec", "des", "stratégies", "de", "dosage", "modifiées."], "label": ["B-Claim", "I-Claim", "I-Claim", "I-Claim", "I-Claim", "I-Claim", "I-Claim", "I-Claim", "I-Claim", "I-Claim", "I-Claim", "I-Claim", "I-Claim", "I-Claim", "I-Claim", "I-Claim", "I-Claim", "I-Claim", "I-Claim", "I-Claim", "I-Claim", "I-Claim", "I-Claim", "I-Claim", "I-Claim"]}
{"text": ["Les", "patients", "de", "l'", "intervention", "ont", "également", "connu", "des", "taux", "plus", "élevés", "de", "traitement", "de", "la", "dépression", "(72,3%", "par", "rapport", "à", "10,4%", "des", "patients", "de", "l'", "EUC", "\";", "\"", "P", "<", "0,0001", "\")", "et", "des", "résultats", "significativement", "meilleurs", "en", "termes", "de", "qualité", "de", "vie,", "y", "compris", "sur", "le", "plan", "social/", "familial", "(différence", "moyenne", "ajustée", "entre", "les", "groupes,", "2,7", "\";", "\"", "95%", "IC,", "1,22", "à", "4,17", "\";", "\"", "P", "<", "0,001", "),", "émotionnel", "(différence", "moyenne", "ajustée,", "1,29", "\";", "\"", "95%", "IC,", "0,26", "à", "2,22", "\";", "\"", "P", "=", "0,01"], "label": ["B-Premise", "I-Premise", "I-Premise", "I-Premise", "I-Premise", "I-Premise", "I-Premise", "I-Premise", "I-Premise", "I-Premise", "I-Premise", "I-Premise", "I-Premise", "I-Premise", "I-Premise", "I-Premise", "I-Premise", "I-Premise", "I-Premise", "I-Premise", "I-Premise", "I-Premise", "I-Premise", "I-Premise", "I-Premise", "I-Premise", "I-Premise", "I-Premise", "I-Premise", "I-Premise", "I-Premise", "I-Premise", "I-Premise", "I-Premise", "I-Premise", "I-Premise", "I-Premise", "I-Premise", "I-Premise", "I-Premise", "I-Premise", "I-Premise", "I-Premise", "I-Premise", "I-Premise", "I-Premise", "I-Premise", "I-Premise", "I-Premise", "I-Premise", "I-Premise", "I-Premise", "I-Premise", "I-Premise", "I-Premise", "I-Premise", "I-Premise", "I-Premise", "I-Premise", "I-Premise", "I-Premise", "I-Premise", "I-Premise", "I-Premise", "I-Premise", "I-Premise", "I-Premise", "I-Premise", "I-Premise", "I-Premise", "I-Premise", "I-Premise", "I-Premise", "I-Premise", "I-Premise", "I-Premise", "I-Premise", "I-Premise", "I-Premise", "I-Premise", "I-Premise", "I-Premise", "I-Premise", "I-Premise", "I-Premise", "I-Premise", "I-Premise", "I-Premise"]}
{"text": ["Pour", "les", "patients", "présentant", "une", "récidive", "de", "la", "maladie", "au", "moins", "6", "mois", "après", "le", "traitement", "initial,", "la", "combinaison", "paclitaxel-platine", "s'", "est", "avérée", "être", "un", "traitement", "supérieur", "à", "la", "monothérapie", "au", "platine."], "label": ["B-Premise", "I-Premise", "I-Premise", "I-Premise", "I-Premise", "I-Premise", "I-Premise", "I-Premise", "I-Premise", "I-Premise", "I-Premise", "I-Premise", "I-Premise", "I-Premise", "I-Premise", "I-Premise", "I-Premise", "I-Premise", "I-Premise", "I-Premise", "I-Premise", "I-Premise", "I-Premise", "I-Premise", "I-Premise", "I-Premise", "I-Premise", "I-Premise", "I-Premise", "I-Premise", "I-Premise", "I-Premise"]}
{"text": ["Des", "interventions", "cliniques", "pour", "traiter", "les", "symptômes", "courants", "associés", "au", "traitement", "devraient", "être", "envisagées", "pour", "améliorer", "le", "fonctionnement", "physique", "et", "émotionnel", "à", "la", "fin", "du", "traitement", "primaire", "du", "cancer", "du", "sein."], "label": ["B-Claim", "I-Claim", "I-Claim", "I-Claim", "I-Claim", "I-Claim", "I-Claim", "I-Claim", "I-Claim", "I-Claim", "I-Claim", "I-Claim", "I-Claim", "I-Claim", "I-Claim", "I-Claim", "I-Claim", "I-Claim", "I-Claim", "I-Claim", "I-Claim", "I-Claim", "I-Claim", "I-Claim", "I-Claim", "I-Claim", "I-Claim", "I-Claim", "I-Claim", "I-Claim", "I-Claim"]}
{"text": ["Les", "différences", "entre", "les", "groupes", "dans", "les", "résultats", "primaires", "n'", "étaient", "pas", "significatives", "à", "12", "mois,", "et", "aucun", "effet", "significatif", "n'", "a", "été", "observé", "sur", "les", "critères", "secondaires."], "label": ["B-Premise", "I-Premise", "I-Premise", "I-Premise", "I-Premise", "I-Premise", "I-Premise", "I-Premise", "I-Premise", "I-Premise", "I-Premise", "I-Premise", "I-Premise", "I-Premise", "I-Premise", "I-Premise", "B-Premise", "I-Premise", "I-Premise", "I-Premise", "I-Premise", "I-Premise", "I-Premise", "I-Premise", "I-Premise", "I-Premise", "I-Premise", "I-Premise"]}
